pdf_lite_mcp-1.0.1.dist-info/licenses/LICENSE
src/__init__.py
src/main.py
src/models.py
src/pdf_reader.py
src/utils.py
pdf_lite_mcp-1.0.1.dist-info/METADATA
pdf_lite_mcp-1.0.1.dist-info/WHEEL
pdf_lite_mcp-1.0.1.dist-info/entry_points.txt
pdf_lite_mcp-1.0.1.dist-info/top_level.txt
pdf_lite_mcp-1.0.1.dist-info/RECORD
