Metadata-Version: 2.4
Name: pdf-lite-mcp
Version: 1.0.1
Summary: A simplified Python MCP server for reading PDF files, optimized for Amazon Q CLI
Author-email: tsaol <tsaol@outlook.com>
License: MIT
Project-URL: Homepage, https://github.com/tsaol/pdf-lite-mcp
Project-URL: Repository, https://github.com/tsaol/pdf-lite-mcp.git
Project-URL: Issues, https://github.com/tsaol/pdf-lite-mcp/issues
Keywords: mcp,pdf,reader,amazon-q,cli
Classifier: Development Status :: 3 - Alpha
Classifier: Intended Audience :: Developers
Classifier: License :: OSI Approved :: MIT License
Classifier: Programming Language :: Python :: 3
Classifier: Programming Language :: Python :: 3.10
Classifier: Programming Language :: Python :: 3.11
Requires-Python: >=3.10
License-File: LICENSE
Requires-Dist: mcp>=1.1.0
Requires-Dist: pydantic>=2.0.0
Requires-Dist: pypdf>=4.0.0
Requires-Dist: requests>=2.31.0
Dynamic: license-file
